{
  "node": {
    "40d9f61982e0383367495f2c6e3ffe436227516aed": {
      "workers": {
        "app/orders/page": {
          "moduleId": "[project]/.next-internal/server/app/orders/page/actions.js { ACTIONS_MODULE0 => \"[project]/src/ai/flows/generate-review-flow.ts [app-rsc] (ecmascript)\" } [app-rsc] (server actions loader, ecmascript)",
          "async": false,
          "exportedName": "generateReview",
          "filename": "src/ai/flows/generate-review-flow.ts"
        }
      },
      "layer": {
        "app/orders/page": "action-browser"
      },
      "exportedName": "generateReview",
      "filename": "src/ai/flows/generate-review-flow.ts"
    }
  },
  "edge": {}
}